cemake/__init__.py
cemake/cemake_build_ext.py
cemake/cemake_extension.py
cemake-0.0.3.dist-info/LICENSE
cemake-0.0.3.dist-info/METADATA
cemake-0.0.3.dist-info/WHEEL
cemake-0.0.3.dist-info/entry_points.txt
cemake-0.0.3.dist-info/top_level.txt
cemake-0.0.3.dist-info/RECORD
