Metadata-Version: 2.1
Name: cemake
Version: 0.0.3
Summary: Allows building of CMake defined Python Extension modules
Home-page: https://github.com/SagaraBattousai/CEMake.git
Author: James Calo
Author-email: jamesafcalo@gmail.com
License: UNKNOWN
Platform: UNKNOWN
Classifier: Programming Language :: Python :: 3.6
Classifier: License :: OSI Approved :: GNU General Public License v3 (GPLv3)
Classifier: Operating System :: OS Independent
Requires-Python: >=3.6
License-File: LICENSE
Requires-Dist: setuptools (>=57.0.0)
